{"ACDC sqr BBS":{"posts":[{"body":"Changed my username, does it look better?","title":"Changed my use","id":"6","time":1623700114,"author":"frozenL"},{"body":"nevermind its 7 letters on the BBS","title":"RE: Changed my","id":"7","time":1623700183,"author":"frozenL"},{"body":"How long has this square been here!? keep finding new things on the net :0","title":"How long has t","id":"8","time":1623704330,"author":"Keriste"},{"body":"hmmm what do you think about       \"frozen Lake\" or \"Frozen Lake\"? it should let you appear as just frozen","title":"RE:RE: Changed","id":"9","time":1623745431,"author":"Anon"},{"body":"we had to FLIP it. TURN-WAYS","title":"TURN-WAYS","id":"10","time":1623801091,"author":"frozenL"},{"body":"See you on the flip side fellow BBS posters!","title":"Flip Side","id":"11","time":1623801160,"author":"D3str0y"},{"body":"See you on the flop side fellow BBS posters!","title":"Flop Side","id":"12","time":1623868282,"author":"Gemini0"},{"body":"testing to see if it still shows my name, please ignore","title":"test","id":"13","time":1623888798,"author":"Gemini0"},{"body":"cool it does lol","title":"cool it does","id":"14","time":1623888807,"author":"Gemini0"},{"body":"Heya!","title":"Heya!","id":"15","time":1623928121,"author":"Ms.Mary"},{"body":"Official IPC Test","title":"Thank you for","id":"16","time":1623965010,"author":"IPC_IJU"},{"body":"How do you do, my fellow netbattlers?","title":"Hello freindos","id":"17","time":1624134428,"author":"Wheeler"},{"body":"WHEELER! I think this is the first time I've seen you on here! :P ","title":"RE:Hello frein","id":"18","time":1624158200,"author":"jameski"},{"body":"SUP","title":"SUP","id":"19","time":1628049609,"author":"Traweez"},{"body":"poopy","title":"poopy ;P","id":"20","time":1628586864,"author":"Keriste"},{"body":"GUILMON WAS HERE","title":"GUILMON WAS HE","id":"21","time":1629498042,"author":"MintFla"},{"body":"Anyone know if ACDC from BN5 is somewhere in this server?","title":"BN5 ACDC?","id":"22","time":1630053415,"author":"Beaned"},{"body":"nvm ignore that lol","title":"ignore that","id":"23","time":1630184928,"author":"Beaned"},{"body":"Test","title":"Test","id":"24","time":1630282356,"author":"RogueCl"},{"body":"Hello Friend! how are you liking bn3 server >:}","title":"Hello Friend! ","id":"25","time":1630363900,"author":"Anon"},{"body":"Hello! While BN3 isn't my favorite of the series, this is still super incredible and I'm having an awesome time. I wish the PvP would work, that'd be fun!","title":"Re: Hello Frie","id":"26","time":1630363994,"author":"Garrulo"},{"body":"It hopefully will be fixed by james soon and what is your favorite? i also have a bn2 server >:}","title":"Re: Hello Frie","id":"27","time":1630364056,"author":"Anon"},{"body":"BN2 was my first BN game, but I think I like 5 the most. Liberation missions and all the playable charactes are really cool! Team Colonel all the way. And that sounds good!","title":"Re: Hello Frie","id":"28","time":1630364149,"author":"Garrulo"},{"body":"I just finished my first custom battle sprites! The amount of ways of customising your navi is awesome!","title":"Navi Sprites","id":"29","time":1630425782,"author":"Beaned"},{"body":"OMG I want to see your custom navi!","title":"Re: Navi Sprit","id":"30","time":1631078945,"author":"Anon"},{"body":"Yeah I've been putting that off but there's lots of cool things in the next update! ...including PVP fixes!","title":"RE:BrokePVP","id":"31","time":1632636737,"author":"Anon"},{"body":"This is the coolest thing ever!!!","title":"This is rad!","id":"32","time":1635715294,"author":"Anon"},{"body":"boo-womp >:)","title":"boo-womp >:)","id":"33","time":1640986216,"author":"Beaned"},{"body":"This is a test post from Rune <3","title":"This is a test","id":"34","time":1640991001,"author":"Anon"},{"body":"Circumcision","title":"Circusman","id":"35","time":1641252623,"author":"Goobomb"}],"next_id":36},"ACDC sqr BBS 2":{"posts":[{"body":"aaah a fresh new board. would be a shame if someone started posting to it.","title":"NEW BOARD","id":"1","time":1623864728,"author":"Gemini0"},{"body":"we need brackets and parentheses and stuff {}()><","title":"brackets","id":"2","time":1623868336,"author":"Gemini0"},{"body":"Yeah I want ascii emotes, there's a fonts.png and fonts.animation if you want to add them to the game. If you do, make a PR or post them in contributions!","title":"RE: brackets","id":"3","time":1623902825,"author":"Anon"},{"body":"I added brackets for you guys and a bunch of other special symbols","title":"RE:RE:brackets","id":"4","time":1624155172,"author":"jameski"},{"body":"holla holla get $","title":"RE:RE:RE:brack","id":"5","time":1624200169,"author":"Poly"},{"body":"Hey, did you guys hear? They're phasing out Zenny in favor of this new currency... they call it \"Monies\". $","title":"New currency?","id":"6","time":1624200851,"author":"Gemini0"},{"body":"Phasing out?\nI was broke with zenny, now I'm broke with $onies ~_~","title":"RE: New curren","id":"7","time":1624321620,"author":"gem  "},{"body":"Last post was me, did not realize I needed to delete my profile.bin to get my name back.","title":"Last post me","id":"8","time":1624321839,"author":"konst"},{"body":"\\(|_|)/\nI think something is wrong with cat eyed kirby.","title":"\\(|_|)/","id":"9","time":1624368427,"author":"frozenL"},{"body":"I found MerchWares item in ACDC. How do I give it to the merchant??","title":"MerchWares hel","id":"10","time":1629145288,"author":"jameski"},{"body":"Seems like the prog supposed to be the Merchant in ACDC 2 gives a different response after you have the MerchWares but still doesn't sell anything, still WIP maybe?","title":"MerchWares dia","id":"11","time":1629819701,"author":"Anon"},{"body":"Hi Nate","title":"Hi Nate","id":"12","time":1639892667,"author":"Jameski"},{"body":"Circumcision","title":"Circusman","id":"13","time":1641252640,"author":"Goobomb"},{"body":"zzz","title":"zzzxx ","id":"14","time":1641308642,"author":"Anon"},{"body":"  hi   enkenaxi   ","title":"  hi   enkenax","id":"15","time":1641308686,"author":"Anon"},{"body":"uwu","title":"uwu","id":"16","time":1641826311,"author":"spdrbyt"},{"body":"Hi","title":"Hi","id":"17","time":1642154948,"author":"Enzan"},{"body":"wow this works ","title":"wow this works","id":"18","time":1642285137,"author":"Dass"},{"body":"Greetings from NettoHikari!","title":"Greetings!!!","id":"19","time":1642482798,"author":"Anon"}],"next_id":20},"11":{"posts":[{"body":"Hello Yoka Square, This is D3str0y3d Your supreme undernet Over Lord this is the location for all the news on the coop","title":"Hello Yoka Squ","id":"1","time":1623228959,"author":"frozenL"},{"body":"test","title":"test","id":"2","time":1623228993,"author":"Konstin"},{"body":"NUUUUUUU","title":"NUUUUUUU","id":"3","time":1623228999,"author":"frozenL"},{"body":"help","title":"help","id":"4","time":1623229209,"author":"frozenL"},{"body":"HELP ME PLEASE KONST IM SCARED","title":"HELP ME PLEASE","id":"5","time":1623229432,"author":"frozenL"},{"body":"help me","title":"help me","id":"6","time":1623229916,"author":"frozenL"},{"body":"I lost my modtools in Yoka and don't want to buy one again in Central. Can someone help me find it?","title":"I lost my modt","id":"7","time":1623251622,"author":"Anon"},{"body":"There's a new link to The Iceberg in n0wh3r3!","title":"There's a new ","id":"8","time":1623347458,"author":"konst"},{"body":"based","title":"based","id":"9","time":1623378678,"author":"Ataraxi"}],"next_id":10},"4":{"posts":[{"body":"I love SciLab!","title":"I love SciLab!","id":"1","time":1623350012,"author":"konst"},{"body":"RE: I love SciLab- same it's all coming together!","title":"RE: I love Sci","id":"2","time":1623350058,"author":"jameski"},{"body":"Re: I love SciLab - \"oh yeah it's all coming together\" Love it","title":"Re: I love Sci","id":"3","time":1623350107,"author":"D3str0y"}],"next_id":4},"5":{"posts":[{"body":"hi","title":"hi","id":"1","time":1623235710,"author":"D3str0y"},{"body":"Finally i have broken the curse, I am FREEEEEEEEEE","title":"Finally i have","id":"2","time":1623235960,"author":"D3str0y"},{"body":"We need to give Mr. Lonely some friends","title":"We need to giv","id":"3","time":1623236217,"author":"konst"},{"body":"Re:we need to give Lonely Friends, i Completely Agree i think we should all be friends with lonely!","title":"Re:we need to ","id":"4","time":1623242937,"author":"D3str0y"},{"body":"\"got your nose\"","title":"\"got your nose","id":"5","time":1623243039,"author":"konst"},{"body":"Watch out for mettaurs! They are yellow virii with pickaxe attacks. The best way to beat them is to dodge their wave projectiles!","title":"Watch out for ","id":"6","time":1623251847,"author":"Anon"},{"body":"I wonder what happens if I do this\")","title":"I wonder what ","id":"7","time":1623296099,"author":"frozenL"},{"body":"!@#$%^&*()_+\tQWERTYUIOP{}|[]\\=-`~","title":"!@#$%^&*()_+\tQ","id":"8","time":1623296174,"author":"frozenL"},{"body":"Sorry for the last two spam posts, folks! I had to ensure that nothing was gonna cause the BBS to Crash!","title":"Sorry for the ","id":"9","time":1623296216,"author":"frozenL"},{"body":"RE: frozenL - don't worry I am sure we will find a way to make it crash","title":"RE: frozenL - ","id":"10","time":1623344876,"author":"jameski"},{"body":"already attempting to! i got yall covered!","title":"already attemp","id":"11","time":1623348180,"author":"D3str0y"},{"body":"RE:Frozen L - I have found removing posts directly from the code can break the BBS but solely due to missing ID's","title":"RE:Frozen L - ","id":"12","time":1623348228,"author":"D3str0y"},{"body":"Hello world!","title":"Hello world!","id":"13","time":1623353655,"author":"playerz"},{"body":"RE:Hello world! - Welcome to cyberworld!","title":"RE:Hello world","id":"14","time":1623354522,"author":"jameski"}],"next_id":15},"Beach BBS":{"posts":[{"body":"fresh internet. no viri, no villians, just friends...","title":"fresh internet","id":"1","time":1623807085,"author":"Anon"},{"body":"The internet feels kinda eerie without interactables etc i wonder what it would look like when populat by many players?","title":"Eerie Net","id":"2","time":1630090551,"author":"Grandma"},{"body":"Yeah one day soon!","title":"Yeah one day s","id":"3","time":1632638254,"author":"Anon"},{"body":"I wonder how the net will look like with random encounters, or like one of those popular MMORPGs","title":"Future Net","id":"4","time":1642285328,"author":"Dass"}],"next_id":5},"Undernet Sqr BBS":{"posts":[{"body":"james was here","title":"james was here","id":"1","time":1624134060,"author":"jameski"},{"body":"poly wuz here :3","title":"poly wuz here ","id":"2","time":1624144486,"author":"Poly"},{"body":"As one of the few people who have ventured here after the conveyor update, you are now part of a select group.","title":"Greetings.","id":"3","time":1624368695,"author":"frozenL"},{"body":"After many years of searching i have finally found it!","title":"Years","id":"4","time":1628048208,"author":"D3str0y"},{"body":"How do i get to the Secret Area?","title":"Secret Area?","id":"5","time":1642285553,"author":"Dass"}],"next_id":6},"SciLab sqr BBS":{"posts":[{"body":"Did Anyone else notice that scilab 1 is open? i couldnt tell at first due to all the glowing arrows being off, but its open!","title":"Scilab1?","pin":true,"author":"D3str0y","time":1623401533,"id":"1"},{"body":"What has been going on in the net lately? first a bunch of areas are down, i talked to someone who hasnt seen anyone else for a long time, and the net will randomly go down out of no where","title":"Net issues?","pin":true,"author":"D3str0y","time":1623402030,"id":"2"},{"body":"No Way! ill have to go check it out!","title":"RE: Scilab1","id":"3","time":1623402854,"author":"Anon"},{"body":"Scilab board needs to be shifted slightly. I'm able to walk behind it, but it wasn't designed for that","title":"Adjust Board?","id":"4","time":1623421468,"author":"konst"},{"body":"Do ya like jazz?","title":"Public Survey","id":"5","time":1623452792,"author":"MyNamei"},{"body":"who wants to battle? square up","title":"who wants to b","id":"6","time":1623704600,"author":"jameski"},{"body":"Ey Kid, wanna see some of my subchips? just got some new stock in hehehe","title":"Ey Kid, wanna ","id":"7","time":1623704615,"author":"Keriste"},{"body":"So, in ACDC1, there is this weird time portal... Could a scientist explain this?","title":"Time Portal?","id":"8","time":1623704661,"author":"frozenL"},{"body":"RE: ey kid: - yes I would infact like a few!","title":"RE: Ey kid: - ","id":"9","time":1623804702,"author":"D3str0y"},{"body":"progbob squarepants","title":"progbob square","id":"10","time":1623873807,"author":"Gemini0"},{"body":"How much deditated WAM do you need to run a BBS?","title":"imp. question","id":"11","time":1623874005,"author":"Gemini0"},{"body":"I got a chip named \"XX\" that just fires my Navi's buster. It deals 60 damage... Anyone else seen this?","title":"Strange chip?","id":"12","time":1623876694,"author":"Gemini0"},{"body":"OI YOU!! SHUT YOUR MOUTH AND LOOK AT MY WAD!!","title":"lods of emone","id":"13","time":1623877442,"author":"Gemini0"},{"body":"spoutman/aquaman got drip","title":"spoutman drip","id":"14","time":1623877656,"author":"Gemini0"},{"body":"help im being chased by some zenny in a whirlwind","title":"Virus?","id":"15","time":1623931511,"author":"Gemini0"},{"body":"ACDC is riddled with mettaur viruses","title":"VIRUSES","id":"16","time":1629765496,"author":"jameski"},{"body":"Heh","title":"Heh","id":"17","time":1634152019,"author":"BlueMoo"}],"next_id":18},"Yoka Square BBS":{"posts":[{"body":"Did anyone else noticed the compression tiles for yoka 1 turned on, but for some reason you dont need compression to use them and they look broken? The net seems like its broken now a days","title":"Yoka 1","id":"1","time":1623406998,"author":"Anon"},{"body":"Yeah they seem a bit off but I'm glad they're in. Let me know if you need a compression program btw","title":"RE: Yoka 1","id":"2","time":1623421192,"author":"konst"},{"body":"Wait you have a compression program already?!? If you have a spare one i would love one!","title":"RE:RE: Yoka1 -","id":"3","time":1623432122,"author":"Anon"},{"body":"i have one but im not sharing","title":"RE:RE:RE:Yoka1","id":"4","time":1623446045,"author":"jameski"},{"body":"I mean, it should be included by default in modern navis... I assume most of you are from the portal in ACDC1?","title":"REx4: Yoka 1","id":"5","time":1623704872,"author":"frozenL"},{"body":"REx4:Yoka1 Yeah, for some reason I'm stuck entering through some warp in ACDC1","title":"RExx:Yoka1 Yea","id":"6","time":1623712985,"author":"D3str0y"},{"body":"\\","title":"\\","id":"7","time":1623870101,"author":"Gemini0"},{"body":"WHO IS HERE AFTER v2?! WOO","title":"v2 released!","id":"8","time":1641679213,"author":"Jameski"}],"next_id":9}}